gridappsd_2030_5_client/__init__.py
gridappsd_2030_5_client/client.py
gridappsd_2030_5_client/exceptions.py
gridappsd_2030_5_client/handlers/__init__.py
gridappsd_2030_5_client/handlers/base.py
gridappsd_2030_5_client/utils/__init__.py
gridappsd_2030_5_client/utils/xml_parser.py
gridappsd_2030_5_client-0.2.2.dist-info/METADATA
gridappsd_2030_5_client-0.2.2.dist-info/WHEEL
gridappsd_2030_5_client-0.2.2.dist-info/RECORD
