Metadata-Version: 2.3
Name: gridappsd-2030-5-client
Version: 0.2.2
Summary: IEEE 2030.5 client for GridAppSD
License: BSD-3-Clause
Keywords: gridappsd,ieee2030.5,smart grid,sep2
Author: C. Allwardt
Author-email: 3979063+craig8@users.noreply.github.com
Requires-Python: >=3.8,<4.0
Classifier: Development Status :: 4 - Beta
Classifier: Intended Audience :: Developers
Classifier: License :: OSI Approved :: BSD License
Classifier: Programming Language :: Python :: 3
Classifier: Programming Language :: Python :: 3.8
Classifier: Programming Language :: Python :: 3.9
Classifier: Programming Language :: Python :: 3.10
Classifier: Programming Language :: Python :: 3.11
Classifier: Programming Language :: Python :: 3.12
Classifier: Programming Language :: Python :: 3.13
Requires-Dist: httpx (>=0.24.1,<0.25.0)
Requires-Dist: websockets (>=11.0.3,<12.0.0)
Project-URL: Homepage, https://github.com/GRIDAPPSD/gridappsd-2030-5-client
Project-URL: Repository, https://github.com/GRIDAPPSD/gridappsd-2030-5-client
